CHANGES.rst
CONTRIBUTORS.rst
DEVELOP.rst
LICENSE.GPL
LICENSE.rst
MANIFEST.in
README.rst
setup.cfg
setup.py
docs/conf.py
docs/index.rst
src/abfab/__init__.py
src/abfab.plone.egg-info/PKG-INFO
src/abfab.plone.egg-info/SOURCES.txt
src/abfab.plone.egg-info/dependency_links.txt
src/abfab.plone.egg-info/entry_points.txt
src/abfab.plone.egg-info/namespace_packages.txt
src/abfab.plone.egg-info/not-zip-safe
src/abfab.plone.egg-info/requires.txt
src/abfab.plone.egg-info/top_level.txt
src/abfab/plone/__init__.py
src/abfab/plone/configure.zcml
src/abfab/plone/interfaces.py
src/abfab/plone/permissions.zcml
src/abfab/plone/setuphandlers.py
src/abfab/plone/testing.py
src/abfab/plone/browser/__init__.py
src/abfab/plone/browser/api.py
src/abfab/plone/browser/catalog.py
src/abfab/plone/browser/configure.zcml
src/abfab/plone/locales/README.rst
src/abfab/plone/locales/__init__.py
src/abfab/plone/locales/abfab.plone.pot
src/abfab/plone/locales/update.py
src/abfab/plone/locales/update.sh
src/abfab/plone/locales/en/LC_MESSAGES/abfab.plone.po
src/abfab/plone/profiles/default/browserlayer.xml
src/abfab/plone/profiles/default/catalog.xml
src/abfab/plone/profiles/default/metadata.xml
src/abfab/plone/profiles/default/rolemap.xml
src/abfab/plone/profiles/default/registry/main.xml
src/abfab/plone/profiles/uninstall/browserlayer.xml
src/abfab/plone/tests/__init__.py
src/abfab/plone/tests/test_robot.py
src/abfab/plone/tests/test_setup.py
src/abfab/plone/tests/robot/test_example.robot